[
  {
    "number": 1,
    "word": "carry",
    "definition": "mang theo",
    "pronunciation": "/ňąk√¶r.i/"
  },
  {
    "number": 2,
    "word": "remove",
    "definition": "gŠĽ° bŠĽŹ, cŠĽüi ra",
    "pronunciation": "/r…™ňąmuňźv/"
  },
  {
    "number": 3,
    "word": "pour",
    "definition": "ńĎŠĽē, r√≥t",
    "pronunciation": "/p…Ēňźr/"
  },
  {
    "number": 4,
    "word": "beverage",
    "definition": "ńĎŠĽď uŠĽĎng",
    "pronunciation": "/ňąbev.…ôr.…™d í/"
  },
  {
    "number": 5,
    "word": "light fixture",
    "definition": "thiŠļŅt bŠĽč chiŠļŅu s√°ng, ńĎ√®n",
    "pronunciation": "/ňąla…™t ňĆf…™ks.t É…ôr/"
  },
  {
    "number": 6,
    "word": "install",
    "definition": "lŠļĮp ńĎŠļ∑t",
    "pronunciation": "/…™nňąst…Ēňźl/"
  },
  {
    "number": 7,
    "word": "warehouse",
    "definition": "kho h√†ng",
    "pronunciation": "/ňąwer.ha äs/"
  },
  {
    "number": 8,
    "word": "meeting minutes",
    "definition": "bi√™n bŠļ£n cuŠĽôc hŠĽćp",
    "pronunciation": "/ňąmiňź.t…™Ňč ňąm…™n.…™ts/"
  },
  {
    "number": 9,
    "word": "accounting",
    "definition": "kŠļŅ to√°n",
    "pronunciation": "/…ôňąka än.t…™Ňč/"
  },
  {
    "number": 10,
    "word": "assistant",
    "definition": "trŠĽ£ l√Ĺ",
    "pronunciation": "/…ôňąs…™s.t…ônt/"
  },
  {
    "number": 11,
    "word": "account",
    "definition": "t√†i khoŠļ£n",
    "pronunciation": "/…ôňąka änt/"
  },
  {
    "number": 12,
    "word": "analyst",
    "definition": "nh√† ph√Ęn t√≠ch",
    "pronunciation": "/ňą√¶n.…ôl.…™st/"
  },
  {
    "number": 13,
    "word": "decoration",
    "definition": "ńĎŠĽď trang tr√≠",
    "pronunciation": "/ňĆdek.…ôňąre…™. É…ôn/"
  },
  {
    "number": 14,
    "word": "competent",
    "definition": "c√≥ nńÉng lŠĽĪc",
    "pronunciation": "/ňąk…Ďňźm.p…ô.t…ônt/"
  },
  {
    "number": 15,
    "word": "retreat",
    "definition": "chuyŠļŅn nghŠĽČ d∆įŠĽ°ng, chuyŠļŅn d√£ ngoŠļ°i",
    "pronunciation": "/r…™ňątriňźt/"
  },
  {
    "number": 16,
    "word": "solve",
    "definition": "giŠļ£i quyŠļŅt",
    "pronunciation": "/s…Ďňźlv/"
  },
  {
    "number": 17,
    "word": "departure",
    "definition": "sŠĽĪ khŠĽüi h√†nh",
    "pronunciation": "/d…™ňąp…Ďňźr.t É…ôr/"
  },
  {
    "number": 18,
    "word": "introduction",
    "definition": "lŠĽĚi giŠĽõi thiŠĽáu, phŠļßn mŠĽü ńĎŠļßu",
    "pronunciation": "/ňĆ…™n.tr…ôňąd Ćk. É…ôn/"
  },
  {
    "number": 19,
    "word": "retirement",
    "definition": "sŠĽĪ nghŠĽČ h∆įu",
    "pronunciation": "/r…™ňąta…™…ôr.m…ônt/"
  },
  {
    "number": 20,
    "word": "appointment",
    "definition": "cuŠĽôc hŠļĻn",
    "pronunciation": "/…ôňąp…Ē…™nt.m…ônt/"
  },
  {
    "number": 21,
    "word": "borrow",
    "definition": "vay, m∆įŠĽ£n",
    "pronunciation": "/ňąb…Ďňźr.o ä/"
  },
  {
    "number": 22,
    "word": "brochure",
    "definition": "tŠĽĚ gŠļ•p quŠļ£ng c√°o",
    "pronunciation": "/bro äňą É är/"
  },
  {
    "number": 23,
    "word": "confirmation",
    "definition": "sŠĽĪ x√°c nhŠļ≠n",
    "pronunciation": "/ňĆk…Ďňźn.f…öňąme…™. É…ôn/"
  },
  {
    "number": 24,
    "word": "process",
    "definition": "quy tr√¨nh",
    "pronunciation": "/ňąpr…Ďňź.ses/"
  },
  {
    "number": 25,
    "word": "expense",
    "definition": "chi ph√≠",
    "pronunciation": "/…™kňąspens/"
  },
  {
    "number": 26,
    "word": "finance",
    "definition": "t√†i ch√≠nh",
    "pronunciation": "/ňąfa…™.n√¶ns/"
  },
  {
    "number": 27,
    "word": "correct",
    "definition": "ńĎ√ļng, ch√≠nh x√°c",
    "pronunciation": "/k…ôňąrekt/"
  },
  {
    "number": 28,
    "word": "demonstration",
    "definition": "buŠĽēi tr√¨nh diŠĽÖn",
    "pronunciation": "/ňĆdem.…ônňąstre…™. É…ôn/"
  },
  {
    "number": 29,
    "word": "charge",
    "definition": "sŠļ°c, t√≠nh ph√≠",
    "pronunciation": "/t É…Ďňźrd í/"
  },
  {
    "number": 30,
    "word": "device",
    "definition": "thiŠļŅt bŠĽč",
    "pronunciation": "/d…™ňąva…™s/"
  },
  {
    "number": 31,
    "word": "cost",
    "definition": "tŠĽĎn chi ph√≠",
    "pronunciation": "/k…Ďňźst/"
  },
  {
    "number": 32,
    "word": "extra",
    "definition": "th√™m, phŠĽ•",
    "pronunciation": "/ňąek.str…ô/"
  },
  {
    "number": 33,
    "word": "in charge of",
    "definition": "phŠĽ• tr√°ch",
    "pronunciation": "/…™n ňąt É…Ďňźrd í …ôv/"
  },
  {
    "number": 34,
    "word": "crew",
    "definition": "ńĎŠĽôi, nh√≥m l√†m viŠĽác",
    "pronunciation": "/kruňź/"
  },
  {
    "number": 35,
    "word": "available",
    "definition": "c√≥ sŠļĶn",
    "pronunciation": "/…ôňąve…™.l…ô.b…ôl/"
  },
  {
    "number": 36,
    "word": "depend on",
    "definition": "phŠĽ• thuŠĽôc v√†o",
    "pronunciation": "/d…™ňąpend …Ďňźn/"
  },
  {
    "number": 37,
    "word": "addition",
    "definition": "sŠĽĪ bŠĽē sung",
    "pronunciation": "/…ôňąd…™ É.…ôn/"
  },
  {
    "number": 38,
    "word": "consider",
    "definition": "c√Ęn nhŠļĮc",
    "pronunciation": "/k…ônňąs…™d.…ôr/"
  },
  {
    "number": 39,
    "word": "lower",
    "definition": "hŠļ° thŠļ•p",
    "pronunciation": "/ňąlo ä.…ôr/"
  },
  {
    "number": 40,
    "word": "headquarters",
    "definition": "trŠĽ• sŠĽü ch√≠nh",
    "pronunciation": "/ňąhedňĆkw…Ēňźr.tŐ¨…ôrz/"
  },
  {
    "number": 41,
    "word": "book",
    "definition": "ńĎŠļ∑t chŠĽó",
    "pronunciation": "/b äk/"
  },
  {
    "number": 42,
    "word": "regional",
    "definition": "thuŠĽôc khu vŠĽĪc",
    "pronunciation": "/ňąriňź.d í…ôn.…ôl/"
  },
  {
    "number": 43,
    "word": "performance",
    "definition": "hiŠĽáu suŠļ•t",
    "pronunciation": "/p…öňąf…Ēňźr.m…ôns/"
  },
  {
    "number": 44,
    "word": "advance",
    "definition": "tr∆įŠĽõc, sŠĽõm",
    "pronunciation": "/…ôdňąv√¶ns/"
  },
  {
    "number": 45,
    "word": "payment",
    "definition": "sŠĽĪ thanh to√°n",
    "pronunciation": "/ňąpe…™.m…ônt/"
  },
  {
    "number": 46,
    "word": "required",
    "definition": "ńĎ∆įŠĽ£c y√™u cŠļßu",
    "pronunciation": "/r…™ňąwa…™…ôrd/"
  },
  {
    "number": 47,
    "word": "sign up for",
    "definition": "ńĎńÉng k√Ĺ",
    "pronunciation": "/sa…™n  Ćp f…Ēňźr/"
  },
  {
    "number": 48,
    "word": "competition",
    "definition": "cuŠĽôc thi",
    "pronunciation": "/ňĆk…Ďňźm.p…ôňąt…™ É.…ôn/"
  },
  {
    "number": 49,
    "word": "merchandise",
    "definition": "h√†ng h√≥a",
    "pronunciation": "/ňąm…Ěňź.t É…ôn.da…™s/"
  },
  {
    "number": 50,
    "word": "permit",
    "definition": "giŠļ•y ph√©p",
    "pronunciation": "/ňąp…Ěňź.m…™t/"
  },
  {
    "number": 51,
    "word": "agree",
    "definition": "ńĎŠĽďng √Ĺ",
    "pronunciation": "/…ôňą…°riňź/"
  },
  {
    "number": 52,
    "word": "annual",
    "definition": "hŠļĪng nńÉm",
    "pronunciation": "/ňą√¶n.ju.…ôl/"
  },
  {
    "number": 53,
    "word": "expand",
    "definition": "mŠĽü rŠĽông",
    "pronunciation": "/…™kňąsp√¶nd/"
  },
  {
    "number": 54,
    "word": "take care of",
    "definition": "chńÉm s√≥c, xŠĽ≠ l√Ĺ",
    "pronunciation": "/te…™k ker …ôv/"
  },
  {
    "number": 55,
    "word": "attendee",
    "definition": "ng∆įŠĽĚi tham dŠĽĪ",
    "pronunciation": "/ňĆ√¶t.…ônňądiňź/"
  },
  {
    "number": 56,
    "word": "job opening",
    "definition": "vŠĽč tr√≠ tuyŠĽÉn dŠĽ•ng",
    "pronunciation": "/d í…Ďňźb ňąo ä.p…ôn.…™Ňč/"
  },
  {
    "number": 57,
    "word": "author",
    "definition": "t√°c giŠļ£",
    "pronunciation": "/ňą…Ēňź.őł…ôr/"
  },
  {
    "number": 58,
    "word": "reserve",
    "definition": "ńĎŠļ∑t tr∆įŠĽõc",
    "pronunciation": "/r…™ňąz…Ěňźv/"
  },
  {
    "number": 59,
    "word": "revise",
    "definition": "sŠĽ≠a ńĎŠĽēi",
    "pronunciation": "/r…™ňąva…™z/"
  },
  {
    "number": 60,
    "word": "budget",
    "definition": "ng√Ęn s√°ch",
    "pronunciation": "/ňąb Ćd í.…™t/"
  },
  {
    "number": 61,
    "word": "get rid of",
    "definition": "loŠļ°i bŠĽŹ",
    "pronunciation": "/…°et r…™d …ôv/"
  },
  {
    "number": 62,
    "word": "unfortunately",
    "definition": "thŠļ≠t kh√īng may",
    "pronunciation": "/ Ćnňąf…Ēňźr.t É…ôn.…ôt.li/"
  },
  {
    "number": 63,
    "word": "operation",
    "definition": "hoŠļ°t ńĎŠĽông",
    "pronunciation": "/ňĆ…Ďňź.p…ôňąre…™. É…ôn/"
  },
  {
    "number": 64,
    "word": "application",
    "definition": "ńĎ∆°n xin",
    "pronunciation": "/ňĆ√¶p.l…™ňąke…™. É…ôn/"
  },
  {
    "number": 65,
    "word": "directions",
    "definition": "chŠĽČ dŠļęn",
    "pronunciation": "/d…ôňąrek. É…ônz/"
  },
  {
    "number": 66,
    "word": "owner",
    "definition": "chŠĽß sŠĽü hŠĽĮu",
    "pronunciation": "/ňąo ä.n…ôr/"
  },
  {
    "number": 67,
    "word": "location",
    "definition": "ńĎŠĽča ńĎiŠĽÉm",
    "pronunciation": "/lo äňąke…™. É…ôn/"
  },
  {
    "number": 68,
    "word": "local",
    "definition": "ńĎŠĽča ph∆į∆°ng",
    "pronunciation": "/ňąlo ä.k…ôl/"
  },
  {
    "number": 69,
    "word": "advantage",
    "definition": "lŠĽ£i thŠļŅ",
    "pronunciation": "/…ôdňąv√¶n.t…™d í/"
  },
  {
    "number": 70,
    "word": "rental",
    "definition": "sŠĽĪ cho thu√™",
    "pronunciation": "/ňąren.tŐ¨…ôl/"
  },
  {
    "number": 71,
    "word": "release",
    "definition": "ph√°t h√†nh",
    "pronunciation": "/r…™ňąliňźs/"
  },
  {
    "number": 72,
    "word": "issue",
    "definition": "vŠļ•n ńĎŠĽĀ",
    "pronunciation": "/ňą…™ É.uňź/"
  },
  {
    "number": 73,
    "word": "secure",
    "definition": "ńĎŠļ£m bŠļ£o, ńĎŠļ°t ńĎ∆įŠĽ£c",
    "pronunciation": "/s…™ňąkj är/"
  },
  {
    "number": 74,
    "word": "conduct",
    "definition": "tiŠļŅn h√†nh",
    "pronunciation": "/k…ônňąd Ćkt/"
  },
  {
    "number": 75,
    "word": "negotiate",
    "definition": "ńĎ√†m ph√°n",
    "pronunciation": "/n…™ňą…°o ä. Éi.e…™t/"
  },
  {
    "number": 76,
    "word": "maintenance",
    "definition": "bŠļ£o tr√¨",
    "pronunciation": "/ňąme…™n.t…ô.n…ôns/"
  },
  {
    "number": 77,
    "word": "randomly",
    "definition": "ngŠļęu nhi√™n",
    "pronunciation": "/ňąr√¶n.d…ôm.li/"
  },
  {
    "number": 78,
    "word": "malfunction",
    "definition": "trŠĽ•c trŠļ∑c",
    "pronunciation": "/m√¶lňąf ĆŇčk. É…ôn/"
  },
  {
    "number": 79,
    "word": "complete",
    "definition": "ho√†n th√†nh",
    "pronunciation": "/k…ômňąpliňźt/"
  },
  {
    "number": 80,
    "word": "increase",
    "definition": "tńÉng l√™n",
    "pronunciation": "/…™nňąkriňźs/"
  }
]